{
  "_class": "symbolInstance",
  "do_objectID": "12716C33-7FDF-47BB-BE9E-41BC55C10D28",
  "exportOptions": {
    "_class": "exportOptions",
    "do_objectID": "148C597B-D758-4915-9FA6-C8D4CDEBD8F9",
    "exportFormats": [
    ],
    "includedLayerIds": [
    ],
    "layerOptions": 0,
    "shouldTrim": false
  },
  "frame": {
    "_class": "rect",
    "constrainProportions": false,
    "do_objectID": "41EE3365-B1D1-481C-8BA4-8B2ADBE673C3",
    "height": 41.51724137931033,
    "width": 65.3567251461987,
    "x": 261.4269005847953,
    "y": 10.37931034482758
  },
  "horizontalSpacing": 0,
  "isFlippedHorizontal": false,
  "isFlippedVertical": false,
  "isLocked": false,
  "isVisible": true,
  "layerListExpandedType": 0,
  "name": "user action copy",
  "nameIsFixed": false,
  "overrideValues": [
    {
      "_class": "overrideValue",
      "do_objectID": "AEE782A1-C155-404C-BC45-B7710A1D1546",
      "overrideName": "4E34BB45-DC63-4AC2-A617-D18D359FBA6E_stringValue",
      "value": "Fill With Valid Inputs"
    }
  ],
  "resizingConstraint": 63,
  "resizingType": 0,
  "rotation": 0,
  "scale": 0.5599999999999999,
  "shouldBreakMaskChain": false,
  "style": {
    "_class": "style",
    "blur": {
      "_class": "blur",
      "center": "{0.5, 0.5}",
      "do_objectID": "0337C51C-76B5-4B2D-9524-DF1FA97B71B6",
      "isEnabled": false,
      "motionAngle": 0,
      "radius": 5.600000000000001,
      "type": 0
    },
    "do_objectID": "CCD4E97F-0607-4029-8568-16D584D44FA1",
    "endDecorationType": 0,
    "miterLimit": 10,
    "startDecorationType": 0
  },
  "symbolID": "170BBAD3-43A7-4D60-98DC-BE6048983B92",
  "verticalSpacing": 0
}